saas_co/__init__.py
saas_co/cur.py
saas_co/ec2.py
saas_co/paginate.py
saas_co/session.py
saas_co-1.9.dist-info/METADATA
saas_co-1.9.dist-info/WHEEL
saas_co-1.9.dist-info/top_level.txt
saas_co-1.9.dist-info/RECORD
