Metadata-Version: 2.1
Name: saas-co
Version: 1.9
Home-page: https://github.com/gmyrianthous/example-publish-pypi
Author: David Schwartz
Author-email: david.schwartz@devfactory.com
License: MIT
Keywords: cost optimization cur
Requires-Dist: boto3
Requires-Dist: botocore
Requires-Dist: pandas
Requires-Dist: awswrangler
Requires-Dist: jsonpath-ng
